README.md
setup.py
two_phase/__init__.py
two_phase/flow_utils.py
two_phase/models.py
two_phase/models_utils.py
two_phase/two_phase.py
two_phase/utils.py
two_phase.egg-info/PKG-INFO
two_phase.egg-info/SOURCES.txt
two_phase.egg-info/dependency_links.txt
two_phase.egg-info/requires.txt
two_phase.egg-info/top_level.txt