Metadata-Version: 2.1
Name: two-phase
Version: 0.1.0
Summary: A simple and easy-to-use two-phase flow library.
Home-page: https://github.com/felipecastrotc/two-phase
Author: Felipe de Castro Teixeira Carvalho
Author-email: felipecastrotc@protonmail.ch
License: GPLv3
Platform: UNKNOWN
Classifier: Development Status :: 3 - Alpha
Classifier: License :: OSI Approved :: GNU General Public License v3 (GPLv3)
Classifier: Programming Language :: Python :: 3
Classifier: Programming Language :: Python :: 3.7
Classifier: Topic :: Scientific/Engineering
Classifier: Intended Audience :: Science/Research
